TicTacToe4fun/__about__.py
TicTacToe4fun/__init__.py
TicTacToe4fun/__pycache__/__about__.cpython-38.pyc
TicTacToe4fun/__pycache__/__init__.cpython-38.pyc
TicTacToe4fun/examples/game1.png
TicTacToe4fun/examples/game1.pptx
TicTacToe4fun/game/__init__.py
TicTacToe4fun/game/_game.py
TicTacToe4fun/game/__pycache__/__init__.cpython-38.pyc
TicTacToe4fun/game/__pycache__/_game.cpython-38.pyc
TicTacToe4fun/game/__pycache__/_play.cpython-38.pyc
TicTacToe4fun-0.0.6.dist-info/LICENSE
TicTacToe4fun-0.0.6.dist-info/METADATA
TicTacToe4fun-0.0.6.dist-info/WHEEL
TicTacToe4fun-0.0.6.dist-info/top_level.txt
TicTacToe4fun-0.0.6.dist-info/RECORD
